pydatastructs/__init__.py
pydatastructs/graphs/__init__.py
pydatastructs/graphs/adjacency_list.py
pydatastructs/graphs/adjacency_matrix.py
pydatastructs/graphs/algorithms.py
pydatastructs/graphs/graph.py
pydatastructs/graphs/tests/__init__.py
pydatastructs/graphs/tests/test_adjacency_list.py
pydatastructs/graphs/tests/test_adjacency_matrix.py
pydatastructs/graphs/tests/test_algorithms.py
pydatastructs/linear_data_structures/__init__.py
pydatastructs/linear_data_structures/algorithms.py
pydatastructs/linear_data_structures/arrays.py
pydatastructs/linear_data_structures/linked_lists.py
pydatastructs/linear_data_structures/tests/__init__.py
pydatastructs/linear_data_structures/tests/test_algorithms.py
pydatastructs/linear_data_structures/tests/test_arrays.py
pydatastructs/linear_data_structures/tests/test_linked_lists.py
pydatastructs/miscellaneous_data_structures/__init__.py
pydatastructs/miscellaneous_data_structures/algorithms.py
pydatastructs/miscellaneous_data_structures/binomial_trees.py
pydatastructs/miscellaneous_data_structures/disjoint_set.py
pydatastructs/miscellaneous_data_structures/queue.py
pydatastructs/miscellaneous_data_structures/sparse_table.py
pydatastructs/miscellaneous_data_structures/stack.py
pydatastructs/miscellaneous_data_structures/tests/__init__.py
pydatastructs/miscellaneous_data_structures/tests/test_binomial_trees.py
pydatastructs/miscellaneous_data_structures/tests/test_disjoint_set.py
pydatastructs/miscellaneous_data_structures/tests/test_queue.py
pydatastructs/miscellaneous_data_structures/tests/test_range_query_static.py
pydatastructs/miscellaneous_data_structures/tests/test_stack.py
pydatastructs/strings/__init__.py
pydatastructs/strings/algorithms.py
pydatastructs/strings/trie.py
pydatastructs/strings/tests/__init__.py
pydatastructs/strings/tests/test_algorithms.py
pydatastructs/strings/tests/test_trie.py
pydatastructs/trees/__init__.py
pydatastructs/trees/binary_trees.py
pydatastructs/trees/heaps.py
cz_pydatastructs-0.0.1.dist-info/AUTHORS
cz_pydatastructs-0.0.1.dist-info/LICENSE
cz_pydatastructs-0.0.1.dist-info/METADATA
cz_pydatastructs-0.0.1.dist-info/WHEEL
cz_pydatastructs-0.0.1.dist-info/top_level.txt
cz_pydatastructs-0.0.1.dist-info/RECORD
