Metadata-Version: 2.1
Name: cz-pydatastructs
Version: 0.0.1
Summary: A python package for data structures
Home-page: https://github.com/codezonediitj/pydatastructs
Author: PyDataStructs Development Team
Author-email: pydatastructs@googlegroups.com
License: UNKNOWN
Platform: UNKNOWN
Classifier: Programming Language :: Python :: 3
Classifier: License :: OSI Approved :: BSD License
Classifier: Operating System :: OS Independent
Classifier: Topic :: Scientific/Engineering
Classifier: Topic :: Scientific/Engineering :: Information Analysis
Classifier: Topic :: Software Development :: Libraries
Requires-Python: >=3.5
License-File: LICENSE
License-File: AUTHORS
